aoc_mod/__init__.py
aoc_mod/interactive.py
aoc_mod/templates/solution_template.py
aoc_mod/utilities.py
aoc_mod-0.2.4.dist-info/METADATA
aoc_mod-0.2.4.dist-info/WHEEL
aoc_mod-0.2.4.dist-info/entry_points.txt
aoc_mod-0.2.4.dist-info/licenses/LICENSE
aoc_mod-0.2.4.dist-info/RECORD
