Metadata-Version: 2.4
Name: aoc_mod
Version: 0.2.4
Summary: A library for Advent of Code containing utilities to use while solving problems!
License-File: LICENSE
Author: David Eyrich
Requires-Python: >=3.11
Classifier: Programming Language :: Python :: 3
Classifier: License :: OSI Approved :: MIT License
Classifier: Operating System :: POSIX :: Linux
Requires-Dist: bandit (>=1.8.6,<2.0.0)
Requires-Dist: beautifulsoup4 (>=4.14.2,<5.0.0)
Requires-Dist: markdownify
Requires-Dist: myst-parser (>=4.0.1,<5.0.0)
Requires-Dist: pytest (>=8.4.2,<9.0.0)
Requires-Dist: requests
Requires-Dist: requests-html (>=0.10.0,<0.11.0)
Requires-Dist: sphinx (>=8.2.3,<9.0.0)
Requires-Dist: sphinx-autoapi (>=3.6.1,<4.0.0)
Requires-Dist: sphinxcontrib-programoutput (>=0.18,<0.19)
Project-URL: Homepage, https://aoc-mod.readthedocs.io/en/latest/
Project-URL: Repository, https://github.com/cosmos1255/aoc_mod
Project-URL: changelog, https://github.com/cosmos1255/aoc_mod/blob/main/CHANGELOG.md
Project-URL: issues, https://github.com/cosmos1255/aoc_mod/issues
